[
  //First row of whirlpools
  {
	"id": 493,
	"x": 2278,
	"z": 10009,
	"radius": 1
  },
  {
	"id": 493,
	"x": 2280,
	"z": 10009,
	"radius": 1
  },
  {
	"id": 493,
	"x": 2286,
	"z": 10006,
	"radius": 1
  },
  {
	"id": 493,
	"x": 2296,
	"z": 10002,
	"radius": 1
  },
  {
	"id": 493,
	"x": 2294,
	"z": 9991,
	"radius": 1
  },
  {
	"id": 493,
	"x": 2267,
	"z": 9996,
	"radius": 4
  },
  {
	"id": 493,
	"x": 2266,
	"z": 9993,
	"radius": 1
  },
  //Second row of whirlpools
  {
	"id": 493,
	"x": 2259,
	"z": 9997,
	"radius": 1
  },
  {
	"id": 493,
	"x": 2259,
	"z": 10017,
	"radius": 1
  },
  {
	"id": 493,
	"x": 2259,
	"z": 10020,
	"radius": 1
  },
  {
	"id": 493,
	"x": 2225,
	"z": 10032,
	"radius": 1
  },
  //Third row of whirlpools
  {
	"id": 493,
	"x": 2255,
	"z": 10030,
	"radius": 2
  },
  //Bloodveld
  {
	"id": 487,
	"x": 2436,
	"z": 9794,
	"radius": 4
  },
  {
	"id": 486,
	"x": 2435,
	"z": 9790,
	"radius": 4
  },
  {
	"id": 487,
	"x": 2431,
	"z": 9788,
	"radius": 4
  },
  {
	"id": 486,
	"x": 2423,
	"z": 9778,
	"radius": 4
  },
  {
	"id": 487,
	"x": 2426,
	"z": 9775,
	"radius": 4
  },
  {
	"id": 486,
	"x": 2424,
	"z": 9774,
	"radius": 4
  },
  {
	"id": 486,
	"x": 2420,
	"z": 9786,
	"radius": 4
  },
  {
	"id": 487,
	"x": 2417,
	"z": 9785,
	"radius": 4
  },
  {
	"id": 486,
	"x": 2415,
	"z": 9786,
	"radius": 4
  },
  //Hellhounds
  {
	"id": 105,
	"x": 2417,
	"z": 9778,
	"radius": 4
  },
  {
	"id": 105,
	"x": 2413,
	"z": 9777,
	"radius": 4
  },
  {
	"id": 105,
	"x": 2415,
	"z": 9774,
	"radius": 4
  },
  {
	"id": 105,
	"x": 2418,
	"z": 9772,
	"radius": 4
  },
  {
	"id": 105,
	"x": 2412,
	"z": 9772,
	"radius": 4
  },
  {
	"id": 105,
	"x": 2410,
	"z": 9781,
	"radius": 4
  },
  {
	"id": 105,
	"x": 2409,
	"z": 9785,
	"radius": 4
  },
  {
	"id": 105,
	"x": 2402,
	"z": 9785,
	"radius": 4
  },
  {
	"id": 105,
	"x": 2402,
	"z": 9782,
	"radius": 4
  },
  //Aberrant Spectre
  {
	"id": 6,
	"x": 2372,
	"z": 9777,
	"radius": 4
  },
  {
	"id": 7,
	"x": 2375,
	"z": 9776,
	"radius": 4
  },
  {
	"id": 6,
	"x": 2375,
	"z": 9771,
	"radius": 4
  },
  {
	"id": 7,
	"x": 2372,
	"z": 9769,
	"radius": 4
  },
  {
	"id": 6,
	"x": 2392,
	"z": 9780,
	"radius": 4
  },
  {
	"id": 6,
	"x": 2395,
	"z": 9776,
	"radius": 4
  },
  {
	"id": 6,
	"x": 2399,
	"z": 9776,
	"radius": 4
  },
  {
	"id": 7,
	"x": 2404,
	"z": 9774,
	"radius": 4
  },
  {
	"id": 7,
	"x": 2384,
	"z": 9777,
	"radius": 4
  },
  {
	"id": 6,
	"x": 2383,
	"z": 9769,
	"radius": 4
  },
  {
	"id": 7,
	"x": 2388,
	"z": 9769,
	"radius": 4
  },
  //Nechryael
  {
	"id": 8,
	"x": 2420,
	"z": 9765,
	"radius": 4
  },
  {
	"id": 8,
	"x": 2420,
	"z": 9763,
	"radius": 4
  },
  {
	"id": 8,
	"x": 2416,
	"z": 9763,
	"radius": 4
  },
  {
	"id": 8,
	"x": 2416,
	"z": 9765,
	"radius": 4
  },
  {
	"id": 8,
	"x": 2410,
	"z": 9766,
	"radius": 4
  },
  {
	"id": 8,
	"x": 2407,
	"z": 9767,
	"radius": 4
  },
  {
	"id": 8,
	"x": 2403,
	"z": 9765,
	"radius": 4
  },
  {
	"id": 8,
	"x": 2408,
	"z": 9762,
	"radius": 4
  },
  {
	"id": 8,
	"x": 2424,
	"z": 9757,
	"radius": 4
  },
  {
	"id": 8,
	"x": 2420,
	"z": 9755,
	"radius": 4
  },
  {
	"id": 8,
	"x": 2423,
	"z": 9753,
	"radius": 4
  },
  {
	"id": 8,
	"x": 2426,
	"z": 9754,
	"radius": 4
  },
  //Abyssal Demons
  {
	"id": 415,
	"x": 2406,
	"z": 9752,
	"radius": 4
  },
  {
	"id": 415,
	"x": 2403,
	"z": 9750,
	"radius": 4
  },
  {
	"id": 415,
	"x": 2406,
	"z": 9748,
	"radius": 4
  },
  {
	"id": 415,
	"x": 2408,
	"z": 9750,
	"radius": 4
  },
  {
	"id": 415,
	"x": 2417,
	"z": 9748,
	"radius": 4
  },
  {
	"id": 415,
	"x": 2414,
	"z": 9745,
	"radius": 4
  },
  {
	"id": 415,
	"x": 2419,
	"z": 9746,
	"radius": 4
  },
  {
	"id": 415,
	"x": 2402,
	"z": 9743,
	"radius": 4
  },
  {
	"id": 415,
	"x": 2402,
	"z": 9740,
	"radius": 4
  },
  {
	"id": 415,
	"x": 2394,
	"z": 9742,
	"radius": 4
  },
  {
	"id": 415,
	"x": 2393,
	"z": 9739,
	"radius": 4
  },
  //Waterfiend
  {
	"id": 2916,
	"x": 2397,
	"z": 9760,
	"radius": 4
  },
  {
	"id": 2916,
	"x": 2395,
	"z": 9758,
	"radius": 4
  },
  {
	"id": 2916,
	"x": 2397,
	"z": 9756,
	"radius": 4
  },
  {
	"id": 2916,
	"x": 2399,
	"z": 9758,
	"radius": 4
  },
  {
	"id": 2916,
	"x": 2386,
	"z": 9761,
	"radius": 4
  },
  {
	"id": 2916,
	"x": 2382,
	"z": 9759,
	"radius": 4
  },
  {
	"id": 2916,
	"x": 2385,
	"z": 9756,
	"radius": 4
  },
  {
	"id": 2916,
	"x": 2389,
	"z": 9759,
	"radius": 4
  },
  {
	"id": 2916,
	"x": 2391,
	"z": 9752,
	"radius": 4
  },
  {
	"id": 2916,
	"x": 2390,
	"z": 9747,
	"radius": 4
  },
  {
	"id": 2916,
	"x": 2384,
	"z": 9748,
	"radius": 4
  },
  {
	"id": 2916,
	"x": 2385,
	"z": 9745,
	"radius": 4
  },
  //Ankou
  {
	"id": 6608,
	"x": 2376,
	"z": 9759,
	"radius": 4
  },
  {
	"id": 6608,
	"x": 2377,
	"z": 9755,
	"radius": 4
  },
  {
	"id": 6608,
	"x": 2377,
	"z": 9750,
	"radius": 4
  },
  {
	"id": 6608,
	"x": 2373,
	"z": 9745,
	"radius": 4
  },
  {
	"id": 6608,
	"x": 2371,
	"z": 9742,
	"radius": 4
  },
  {
	"id": 6608,
	"x": 2375,
	"z": 9741,
	"radius": 4
  },
  //Greater Demons
  {
	"id": 2025,
	"x": 2362,
	"z": 9776,
	"radius": 4
  },
  {
	"id": 2026,
	"x": 2363,
	"z": 9770,
	"radius": 4
  },
  {
	"id": 2027,
	"x": 2365,
	"z": 9763,
	"radius": 4
  },
  {
	"id": 2025,
	"x": 2361,
	"z": 9754,
	"radius": 4
  },
  {
	"id": 2026,
	"x": 2365,
	"z": 9754,
	"radius": 4
  },
  {
	"id": 2027,
	"x": 2362,
	"z": 9750,
	"radius": 4
  },
  {
	"id": 2025,
	"x": 2364,
	"z": 9743,
	"radius": 4
  },
  {
	"id": 2026,
	"x": 2358,
	"z": 9740,
	"radius": 4
  },
  {
	"id": 2027,
	"x": 2358,
	"z": 9735,
	"radius": 4
  },
  //Bronze Dragon
  {
	"id": 270,
	"x": 2349,
	"z": 9733,
	"radius": 4
  },
  {
	"id": 271,
	"x": 2343,
	"z": 9734,
	"radius": 4
  },
  {
	"id": 270,
	"x": 2349,
	"z": 9741,
	"radius": 4
  },
  //Black Dragons
  {
	"id": 252,
	"x": 2330,
	"z": 9747,
	"radius": 4
  },
  {
	"id": 253,
	"x": 2334,
	"z": 9746,
	"radius": 4
  },
  {
	"id": 254,
	"x": 2336,
	"z": 9751,
	"radius": 4
  },
  {
	"id": 255,
	"x": 2336,
	"z": 9757,
	"radius": 4
  },
  {
	"id": 256,
	"x": 2344,
	"z": 9768,
	"radius": 4
  },
  {
	"id": 257,
	"x": 2345,
	"z": 9761,
	"radius": 4
  },
  //Firegiant
  {
	"id": 2075,
	"x": 2356,
	"z": 9762,
	"radius": 4
  },
  {
	"id": 2076,
	"x": 2352,
	"z": 9760,
	"radius": 4
  },
  {
	"id": 2077,
	"x": 2351,
	"z": 9755,
	"radius": 4
  },
  {
	"id": 2075,
	"x": 2355,
	"z": 9768,
	"radius": 4
  },
  {
	"id": 2076,
	"x": 2351,
	"z": 9769,
	"radius": 4
  },
  {
	"id": 2077,
	"x": 2354,
	"z": 9774,
	"radius": 4
  },
  {
	"id": 2078,
	"x": 2350,
	"z": 9776,
	"radius": 4
  },
  {
	"id": 2075,
	"x": 2343,
	"z": 9775,
	"radius": 4
  },
  {
	"id": 2076,
	"x": 2342,
	"z": 9773,
	"radius": 4
  },
  {
	"id": 2077,
	"x": 2337,
	"z": 9776,
	"radius": 4
  },
  {
	"id": 2078,
	"x": 2335,
	"z": 9771,
	"radius": 4
  },
  //Steel Dragon
  {
	"id": 274,
	"x": 2319,
	"z": 9777,
	"radius": 4
  },
  {
	"id": 275,
	"x": 2312,
	"z": 9777,
	"radius": 4
  },
  {
	"id": 274,
	"x": 2314,
	"z": 9773,
	"radius": 4
  },
  {
	"id": 275,
	"x": 2323,
	"z": 9764,
	"radius": 4
  },
  {
	"id": 274,
	"x": 2322,
	"z": 9768,
	"radius": 4
  },
  {
	"id": 275,
	"x": 2318,
	"z": 9761,
	"radius": 4
  },
  //Iron Dragon
  {
	"id": 273,
	"x": 2315,
	"z": 9747,
	"radius": 4
  },
  {
	"id": 273,
	"x": 2311,
	"z": 9743,
	"radius": 4
  },
  {
	"id": 272,
	"x": 2312,
	"z": 9753,
	"radius": 4
  },
  {
	"id": 272,
	"x": 2309,
	"z": 9734,
	"radius": 4
  },
  {
	"id": 273,
	"x": 2315,
	"z": 9734,
	"radius": 4
  },
  {
	"id": 272,
	"x": 2320,
	"z": 9735,
	"radius": 4
  },
  //Blue Dragon
  {
	"id": 265,
	"x": 2249,
	"z": 9754,
	"radius": 4
  },
  {
	"id": 266,
	"x": 2258,
	"z": 9754,
	"radius": 4
  },
  {
	"id": 267,
	"x": 2267,
	"z": 9758,
	"radius": 4
  },
  {
	"id": 268,
	"x": 2271,
	"z": 9747,
	"radius": 4
  },
  {
	"id": 269,
	"x": 2261,
	"z": 9742,
	"radius": 4
  },
  {
	"id": 265,
	"x": 2253,
	"z": 9739,
	"radius": 4
  },
  //Black Demons
  {
	"id": 1432,
	"x": 2298,
	"z": 9772,
	"radius": 4
  },
  {
	"id": 1432,
	"x": 2280,
	"z": 9777,
	"radius": 4
  },
  {
	"id": 1432,
	"x": 2274,
	"z": 9774,
	"radius": 4
  },
  {
	"id": 1432,
	"x": 2266,
	"z": 9769,
	"radius": 4
  },
  {
	"id": 1432,
	"x": 2255,
	"z": 9770,
	"radius": 4
  },
  {
	"id": 1432,
	"x": 2253,
	"z": 9775,
	"radius": 4
  },
  {
	"id": 1432,
	"x": 2262,
	"z": 9781,
	"radius": 4
  },
  {
	"id": 1432,
	"x": 2268,
	"z": 9783,
	"radius": 4
  },
  {
	"id": 1432,
	"x": 2295,
	"z": 9781,
	"radius": 4
  },
  //Black Dragons
  {
	"id": 252,
	"x": 2299,
	"z": 9749,
	"radius": 4
  },
  {
	"id": 253,
	"x": 2295,
	"z": 9741,
	"radius": 4
  },
  {
	"id": 254,
	"x": 2290,
	"z": 9742,
	"radius": 4
  },
  {
	"id": 255,
	"x": 2290,
	"z": 9742,
	"radius": 4
  },
  {
	"id": 256,
	"x": 2286,
	"z": 9753,
	"radius": 4
  },
  //Added-on dungeon with smoke devils
  {
	"id": 498,
	"x": 2401,
	"z": 9426,
	"radius": 4
  },
  {
	"id": 498,
	"x": 2404,
	"z": 9429,
	"radius": 4
  },
  {
	"id": 498,
	"x": 2410,
	"z": 9428,
	"radius": 4
  },
  {
	"id": 498,
	"x": 2408,
	"z": 9434,
	"radius": 4
  },
  {
	"id": 498,
	"x": 2410,
	"z": 9438,
	"radius": 4
  },
  {
	"id": 498,
	"x": 2404,
	"z": 9438,
	"radius": 4
  },
  {
	"id": 498,
	"x": 2397,
	"z": 9442,
	"radius": 4
  },
  {
	"id": 498,
	"x": 2394,
	"z": 9440,
	"radius": 4
  },
  {
	"id": 498,
	"x": 2388,
	"z": 9449,
	"radius": 4
  },
  {
	"id": 498,
	"x": 2414,
	"z": 9462,
	"radius": 4
  },
  {
	"id": 498,
	"x": 2415,
	"z": 9458,
	"radius": 4
  },
  {
	"id": 498,
	"x": 2412,
	"z": 9447,
	"radius": 4
  },
  {
	"id": 498,
	"x": 2407,
	"z": 9457,
	"radius": 4
  },
  {
	"id": 498,
	"x": 2407,
	"z": 9453,
	"radius": 4
  },
  {
	"id": 498,
	"x": 2405,
	"z": 9457,
	"radius": 4
  },
  {
	"id": 498,
	"x": 2400,
	"z": 9453,
	"radius": 4
  },
  {
	"id": 498,
	"x": 2400,
	"z": 9457,
	"radius": 4
  },
  {
	"id": 498,
	"x": 2394,
	"z": 9462,
	"radius": 4
  },
  {
	"id": 498,
	"x": 2394,
	"z": 9461,
	"radius": 4
  },
  {
	"id": 498,
	"x": 2382,
	"z": 9463,
	"radius": 4
  },
  {
	"id": 498,
	"x": 2380,
	"z": 9463,
	"radius": 4
  },
  {
	"id": 498,
	"x": 2384,
	"z": 9435,
	"radius": 4
  },
  {
	"id": 498,
	"x": 2418,
	"z": 9457,
	"radius": 4
  },
  {
	"id": 498,
	"x": 2416,
	"z": 9462,
	"radius": 4
  },
  {
	"id": 498,
	"x": 2422,
	"z": 9453,
	"radius": 4
  },
  {
	"id": 498,
	"x": 2420,
	"z": 9448,
	"radius": 4
  },
  {
	"id": 498,
	"x": 2392,
	"z": 9447,
	"radius": 4
  },
  {
	"id": 498,
	"x": 2388,
	"z": 9447,
	"radius": 4
  },
  {
	"id": 498,
	"x": 2389,
	"z": 9449,
	"radius": 4
  },
  {
	"id": 498,
	"x": 2413,
	"z": 9424,
	"radius": 4
  },
  {
	"id": 498,
	"x": 2419,
	"z": 9425,
	"radius": 4
  },
  {
	"id": 498,
	"x": 2418,
	"z": 9419,
	"radius": 4
  },
  //Thermonuclear smoke devil boss room
  {
	"id": 499,
	"x": 2363,
	"z": 9450,
	"radius": 3
  },
  {
	"id": 498,
	"x": 2357,
	"z": 9445,
	"radius": 4
  },
  {
	"id": 498,
	"x": 2355,
	"z": 9448,
	"radius": 4
  },
  {
	"id": 498,
	"x": 2359,
	"z": 9443,
	"radius": 4
  },
  {
	"id": 498,
	"x": 2365,
	"z": 9445,
	"radius": 4
  },
  {
	"id": 498,
	"x": 2370,
	"z": 9444,
	"radius": 4
  },
  {
	"id": 498,
	"x": 2369,
	"z": 9441,
	"radius": 4
  },
  {
	"id": 498,
	"x": 2374,
	"z": 9446,
	"radius": 4
  },
  {
	"id": 498,
	"x": 2372,
	"z": 9455,
	"radius": 4
  },
  {
	"id": 498,
	"x": 2367,
	"z": 9452,
	"radius": 4
  },
  {
	"id": 498,
	"x": 2365,
	"z": 9452,
	"radius": 4
  },
  {
	"id": 498,
	"x": 2359,
	"z": 9448,
	"radius": 4
  },
  {
	"id": 498,
	"x": 2365,
	"z": 9448,
	"radius": 4
  },
  //Kraken boss
  
  {
	"id": 496,
	"x": 2278,
	"z": 10034,
	"radius": 0
  }
  // Kraken Whirlpool. Has a onSpawn trigger to spawn minions
]